.gitignore
.mergify.yml
.pre-commit-config.yaml
.travis.yml
AUTHORS
README.md
lgpl-2.1.txt
pyproject.toml
setup.cfg
setup.py
cython_iscsi.egg-info/PKG-INFO
cython_iscsi.egg-info/SOURCES.txt
cython_iscsi.egg-info/dependency_links.txt
cython_iscsi.egg-info/requires.txt
cython_iscsi.egg-info/top_level.txt
src/iscsi.c
src/iscsi.pyx
tests/__init__.py
tests/iscsi_test.py