Metadata-Version: 2.1
Name: cython-iscsi
Version: 1.0
Summary: Cython-based wrapper for libiscsi.
Home-page: https://github.com/python-scsi/cython-iscsi
Maintainer: Markus Rosjat
Maintainer-email: markus.rosjat@gmail.com
License: LGPL-2.1+
Keywords: scsi iscsi
Platform: UNKNOWN
Classifier: Programming Language :: Python
Classifier: Programming Language :: Python :: 3
Classifier: Development Status :: 4 - Beta
Classifier: License :: OSI Approved :: GNU Lesser General Public License v2 or later (LGPLv2+)
Provides-Extra: dev
